model_checker/README.md
model_checker/__init__.py
model_checker/__main__.py
model_checker/cli.py
model_checker/builder/README.md
model_checker/builder/__init__.py
model_checker/builder/comparison.py
model_checker/builder/detector.py
model_checker/builder/error_types.py
model_checker/builder/errors.py
model_checker/builder/example.py
model_checker/builder/filesystem.py
model_checker/builder/importer.py
model_checker/builder/loader.py
model_checker/builder/module.py
model_checker/builder/project.py
model_checker/builder/protocols.py
model_checker/builder/runner.py
model_checker/builder/runner_utils.py
model_checker/builder/serialize.py
model_checker/builder/strategies.py
model_checker/builder/translation.py
model_checker/builder/types.py
model_checker/builder/validation.py
model_checker/builder/z3_utils.py
model_checker/builder/tests/README.md
model_checker/builder/tests/__init__.py
model_checker/builder/tests/conftest.py
model_checker/builder/tests/improvements.md
model_checker/builder/tests/test_issue_73_fix.py
model_checker/builder/tests/test_package_loading.py
model_checker/builder/tests/test_refactoring_current_behavior.py
model_checker/builder/tests/test_refactoring_target_behavior.py
model_checker/builder/tests/e2e/test_full_pipeline.py
model_checker/builder/tests/e2e/test_project_edge_cases.py
model_checker/builder/tests/fixtures/__init__.py
model_checker/builder/tests/fixtures/assertions.py
model_checker/builder/tests/fixtures/mock_objects.py
model_checker/builder/tests/fixtures/temp_resources.py
model_checker/builder/tests/fixtures/test_data.py
model_checker/builder/tests/integration/README.md
model_checker/builder/tests/integration/test_build_module_theories.py
model_checker/builder/tests/integration/test_cli_interactive_integration.py
model_checker/builder/tests/integration/test_component_integration.py
model_checker/builder/tests/integration/test_error_propagation.py
model_checker/builder/tests/integration/test_generated_projects.py
model_checker-1.2.12.dist-info/licenses/LICENSE
model_checker-1.2.12.dist-info/METADATA
model_checker-1.2.12.dist-info/WHEEL
model_checker-1.2.12.dist-info/entry_points.txt
model_checker-1.2.12.dist-info/top_level.txt
model_checker-1.2.12.dist-info/RECORD
