Metadata-Version: 2.4
Name: model-checker
Version: 1.2.12
Summary: A hyperintensional theorem prover for developing and and exploring programmatic semantic theories.
Author-email: Benjamin Brast-McKie <benbrastmckie@gmail.com>
License: GPL-3.0-or-later
Project-URL: Homepage, https://github.com/benbrastmckie/ModelChecker
Project-URL: Issues, https://github.com/benbrastmckie/ModelChecker/issues
Keywords: semantics,Z3,logic,counterfactuals,modality,model checker,theorem prover,hyperintensionality
Classifier: Programming Language :: Python :: 3.8
Classifier: License :: OSI Approved :: GNU General Public License v3 or later (GPLv3+)
Classifier: Operating System :: OS Independent
Requires-Python: >=3.8
License-File: LICENSE
Requires-Dist: z3-solver>=4.8.0
Requires-Dist: networkx>=2.0
Provides-Extra: jupyter
Requires-Dist: ipywidgets>=7.0.0; extra == "jupyter"
Requires-Dist: matplotlib>=3.0.0; extra == "jupyter"
Requires-Dist: networkx>=2.0; extra == "jupyter"
Requires-Dist: jupyter; extra == "jupyter"
Requires-Dist: ipython; extra == "jupyter"
Provides-Extra: all
Requires-Dist: ipywidgets>=7.0.0; extra == "all"
Requires-Dist: matplotlib>=3.0.0; extra == "all"
Requires-Dist: networkx>=2.0; extra == "all"
Requires-Dist: jupyter; extra == "all"
Requires-Dist: ipython; extra == "all"
Dynamic: license-file
